module.py
winterm-0.0.1a1.dist-info/LICENSE
winterm-0.0.1a1.dist-info/METADATA
winterm-0.0.1a1.dist-info/WHEEL
winterm-0.0.1a1.dist-info/top_level.txt
winterm-0.0.1a1.dist-info/RECORD
